boris/__init__.py
boris/app.py
boris/cli.py
boris/config.py
boris/logging_config.py
boris/render.py
boris/boriscore/__init__.py
boris/boriscore/agent/__init__.py
boris/boriscore/agent/coding_agent.py
boris/boriscore/agent/models.py
boris/boriscore/agent/prompts.py
boris/boriscore/agent/toolbox.py
boris/boriscore/agent/utils.py
boris/boriscore/agent/toolboxes/toolbox.json
boris/boriscore/ai_clients/__init__.py
boris/boriscore/ai_clients/ai_clients.py
boris/boriscore/ai_clients/models.py
boris/boriscore/ai_clients/utils.py
boris/boriscore/code_structurer/__init__.py
boris/boriscore/code_structurer/code_manager.py
boris/boriscore/code_structurer/code_nodes.py
boris/boriscore/code_structurer/models.py
boris/boriscore/code_structurer/prompts.py
boris/boriscore/code_structurer/toolbox.py
boris/boriscore/code_structurer/utils.py
boris/boriscore/code_structurer/toolboxes/toolbox.json
boris/boriscore/terminal/__init__.py
boris/boriscore/terminal/models.py
boris/boriscore/terminal/terminal_interface.py
boris/boriscore/toolbox_mngmnt/__init__.py
boris/boriscore/toolbox_mngmnt/toolbox.py
boris/boriscore/utils/resources.py
boris/boriscore/utils/snapshots.py
boris/boriscore/utils/tracing.py
boris/boriscore/utils/utils.py
boris/engines/__init__.py
boris/engines/base.py
boris/engines/local.py
boris/engines/prompts.py
boris/engines/remote.py
boris/engines/toolbox.py
boris/engines/toolboxes/toolbox.json
boris/tests/simulate_tool_call.py
boris/tests/test_cli.py
boris/tests/test_code_nodes.py
boris/tests/test_coding_writer.py
boris/tests/test_git_interface.py
boris/tests/test_local_engine.py
boris/tests/test_terminal.py
boris_cli-0.1.3.dist-info/licenses/LICENSE
boris_cli-0.1.3.dist-info/METADATA
boris_cli-0.1.3.dist-info/WHEEL
boris_cli-0.1.3.dist-info/entry_points.txt
boris_cli-0.1.3.dist-info/top_level.txt
boris_cli-0.1.3.dist-info/RECORD
