Metadata-Version: 2.4
Name: boris-cli
Version: 0.1.3
Summary: Terminal-first AI coding/chat assistant with safe shell tools.
Author-email: Riccardo Tordini <tordiniriccardo@gmail.com>
License: BORIS PERSONAL USE LICENSE
Project-URL: Homepage, https://github.com/applebar17/Boris
Keywords: cli,ai,chat,terminal,coding,assistant,boris,boris-cli
Classifier: License :: OSI Approved :: MIT License
Classifier: Programming Language :: Python :: 3
Classifier: Programming Language :: Python :: 3.10
Classifier: Programming Language :: Python :: 3.11
Classifier: Programming Language :: Python :: 3.12
Classifier: Environment :: Console
Classifier: Intended Audience :: Developers
Requires-Python: >=3.10
License-File: LICENSE
Requires-Dist: typer>=0.12
Requires-Dist: platformdirs>=4.2.0
Requires-Dist: rich>=13
Requires-Dist: prompt-toolkit>=3.0
Requires-Dist: pydantic>=2
Requires-Dist: typing-extensions>=4.11
Requires-Dist: httpx>=0.27
Requires-Dist: openai>=1.107.2
Requires-Dist: python-dotenv>=1.0.0
Requires-Dist: tomli; python_version < "3.11"
Requires-Dist: pathspec>=0.12.1
Requires-Dist: langsmith>=0.4.27
Requires-Dist: tiktoken>=0.11.0
Requires-Dist: ulid>=1.1
Provides-Extra: dev
Requires-Dist: pytest>=8; extra == "dev"
Requires-Dist: pytest-cov>=4; extra == "dev"
Requires-Dist: ruff>=0.5; extra == "dev"
Requires-Dist: mypy>=1.10; extra == "dev"
Requires-Dist: pexpect>=4.9.0; extra == "dev"
Requires-Dist: sqlite-utils>=3; extra == "dev"
Requires-Dist: langsmith>=0.4.27; extra == "dev"
Dynamic: license-file
